<?xml version="1.0"?>
<Ontology xmlns="http://www.w3.org/2002/07/owl#"
     xml:base="https://vsr.informatik.tu-chemnitz.de/ontologies/source_knowledge"
     xmlns:rdf="http://www.w3.org/1999/02/22-rdf-syntax-ns#"
     xmlns:xml="http://www.w3.org/XML/1998/namespace"
     xmlns:xsd="http://www.w3.org/2001/XMLSchema#"
     xmlns:rdfs="http://www.w3.org/2000/01/rdf-schema#"
     ontologyIRI="https://vsr.informatik.tu-chemnitz.de/ontologies/source_knowledge">
    <Prefix name="" IRI="https://vsr.informatik.tu-chemnitz.de/ontologies/source_knowledge#"/>
    <Prefix name="dc" IRI="http://purl.org/dc/elements/1.1/"/>
    <Prefix name="oa" IRI="http://www.w3.org/ns/oa#"/>
    <Prefix name="kdm" IRI="http://schema.omg.org/spec/KDM/1.2/kdm"/>
    <Prefix name="owl" IRI="http://www.w3.org/2002/07/owl#"/>
    <Prefix name="rdf" IRI="http://www.w3.org/1999/02/22-rdf-syntax-ns#"/>
    <Prefix name="xml" IRI="http://www.w3.org/XML/1998/namespace"/>
    <Prefix name="xsd" IRI="http://www.w3.org/2001/XMLSchema#"/>
    <Prefix name="rdfs" IRI="http://www.w3.org/2000/01/rdf-schema#"/>
    <Prefix name="sckm" IRI="https://vsr.informatik.tu-chemnitz.de/ontologies/source_knowledge#"/>
    <Prefix name="swrl" IRI="http://www.w3.org/2003/11/swrl#"/>
    <Prefix name="swrla" IRI="http://swrl.stanford.edu/ontologies/3.3/swrla.owl#"/>
    <Prefix name="swrlb" IRI="http://www.w3.org/2003/11/swrlb#"/>
    <Prefix name="dcterms" IRI="http://purl.org/dc/terms/"/>
    <Annotation>
        <AnnotationProperty abbreviatedIRI="dc:contributor"/>
        <Literal xml:lang="en">Fariba Quarib</Literal>
    </Annotation>
    <Annotation>
        <AnnotationProperty abbreviatedIRI="dc:contributor"/>
        <Literal xml:lang="de">Justin Förster</Literal>
    </Annotation>
    <Annotation>
        <AnnotationProperty abbreviatedIRI="dc:creator"/>
        <Literal xml:lang="en">Sebastian Heil</Literal>
    </Annotation>
    <Annotation>
        <AnnotationProperty abbreviatedIRI="dc:subject"/>
        <Literal xml:lang="en">annotation</Literal>
    </Annotation>
    <Annotation>
        <AnnotationProperty abbreviatedIRI="dc:subject"/>
        <Literal xml:lang="en">source code</Literal>
    </Annotation>
    <Annotation>
        <AnnotationProperty abbreviatedIRI="dc:title"/>
        <Literal xml:lang="en">SCKM Ontology</Literal>
    </Annotation>
    <Annotation>
        <AnnotationProperty abbreviatedIRI="dcterms:license"/>
        <Literal xml:lang="en">MIT License Copyright (c) 2019 Technische Universität Chemnitz Permission is hereby granted, free of charge, to any person obtaining a copy of this software and associated documentation files (the &quot;Software&quot;), to deal in the Software without restriction, including without limitation the rights to use, copy, modify, merge, publish, distribute, sublicense, and/or sell copies of the Software, and to permit persons to whom the Software is furnished to do so, subject to the following conditions: The above copyright notice and this permission notice shall be included in all copies or substantial portions of the Software. THE SOFTWARE IS PROVIDED &quot;AS IS&quot;, WITHOUT WARRANTY OF ANY KIND, EXPRESS OR IMPLIED, INCLUDING BUT NOT LIMITED TO THE WARRANTIES OF MERCHANTABILITY, FITNESS FOR A PARTICULAR PURPOSE AND NONINFRINGEMENT. IN NO EVENT SHALL THE AUTHORS OR COPYRIGHT HOLDERS BE LIABLE FOR ANY CLAIM, DAMAGES OR OTHER LIABILITY, WHETHER IN AN ACTION OF CONTRACT, TORT OR OTHERWISE, ARISING FROM, OUT OF OR IN CONNECTION WITH THE SOFTWARE OR THE USE OR OTHER DEALINGS IN THE SOFTWARE.</Literal>
    </Annotation>
    <Annotation>
        <AnnotationProperty abbreviatedIRI="rdfs:comment"/>
        <Literal xml:lang="en">This ontology is an OWL representation of the source code knowledge model (SCKM) formalism, which is part of the AWSM Reverse Engineering method (AWSM:RE). It employs the W3C Web Annotation standard.</Literal>
    </Annotation>
    <Annotation>
        <AnnotationProperty abbreviatedIRI="rdfs:seeAlso"/>
        <IRI>https://www.w3.org/TR/annotation-vocab/</IRI>
    </Annotation>
    <Annotation>
        <AnnotationProperty abbreviatedIRI="rdfs:seeAlso"/>
        <IRI>﻿http://www.omg.org/spec/KDM/1.3/</IRI>
    </Annotation>
    <Declaration>
        <Class abbreviatedIRI="oa:Annotation"/>
    </Declaration>
    <Declaration>
        <Class abbreviatedIRI="oa:SpecificResource"/>
    </Declaration>
    <Declaration>
        <Class abbreviatedIRI="oa:TextPositionSelector"/>
    </Declaration>
    <Declaration>
        <Class IRI="#Algorithm"/>
    </Declaration>
    <Declaration>
        <Class IRI="#Area"/>
    </Declaration>
    <Declaration>
        <Class IRI="#BusinessProccess"/>
    </Declaration>
    <Declaration>
        <Class IRI="#Configuration"/>
    </Declaration>
    <Declaration>
        <Class IRI="#Deployment"/>
    </Declaration>
    <Declaration>
        <Class IRI="#DomainKnowledge"/>
    </Declaration>
    <Declaration>
        <Class IRI="#Explanatory"/>
    </Declaration>
    <Declaration>
        <Class IRI="#Feature"/>
    </Declaration>
    <Declaration>
        <Class IRI="#Persistence"/>
    </Declaration>
    <Declaration>
        <Class IRI="#Presentation"/>
    </Declaration>
    <Declaration>
        <Class IRI="#Rule"/>
    </Declaration>
    <Declaration>
        <ObjectProperty abbreviatedIRI="oa:hasBody"/>
    </Declaration>
    <Declaration>
        <ObjectProperty abbreviatedIRI="oa:hasSelector"/>
    </Declaration>
    <Declaration>
        <ObjectProperty abbreviatedIRI="oa:hasTarget"/>
    </Declaration>
    <Declaration>
        <ObjectProperty IRI="#influences"/>
    </Declaration>
    <Declaration>
        <ObjectProperty IRI="#requires"/>
    </Declaration>
    <Declaration>
        <ObjectProperty IRI="#within"/>
    </Declaration>
    <Declaration>
        <DataProperty abbreviatedIRI="oa:end"/>
    </Declaration>
    <Declaration>
        <DataProperty abbreviatedIRI="oa:hasSource"/>
    </Declaration>
    <Declaration>
        <DataProperty abbreviatedIRI="oa:start"/>
    </Declaration>
    <Declaration>
        <DataProperty IRI="#name"/>
    </Declaration>
    <Declaration>
        <AnnotationProperty abbreviatedIRI="dc:contributor"/>
    </Declaration>
    <Declaration>
        <AnnotationProperty abbreviatedIRI="dc:creator"/>
    </Declaration>
    <Declaration>
        <AnnotationProperty abbreviatedIRI="dc:subject"/>
    </Declaration>
    <Declaration>
        <AnnotationProperty abbreviatedIRI="dc:title"/>
    </Declaration>
    <Declaration>
        <AnnotationProperty abbreviatedIRI="dcterms:license"/>
    </Declaration>
    <Declaration>
        <AnnotationProperty abbreviatedIRI="swrla:isRuleEnabled"/>
    </Declaration>
    <EquivalentClasses>
        <Class abbreviatedIRI="oa:SpecificResource"/>
        <Class IRI="#Area"/>
    </EquivalentClasses>
    <SubClassOf>
        <Class IRI="#Algorithm"/>
        <Class IRI="#DomainKnowledge"/>
    </SubClassOf>
    <SubClassOf>
        <Class IRI="#BusinessProccess"/>
        <Class IRI="#DomainKnowledge"/>
    </SubClassOf>
    <SubClassOf>
        <Class IRI="#Configuration"/>
        <Class IRI="#DomainKnowledge"/>
    </SubClassOf>
    <SubClassOf>
        <Class IRI="#Deployment"/>
        <Class IRI="#DomainKnowledge"/>
    </SubClassOf>
    <SubClassOf>
        <Class IRI="#Explanatory"/>
        <Class IRI="#DomainKnowledge"/>
    </SubClassOf>
    <SubClassOf>
        <Class IRI="#Persistence"/>
        <Class IRI="#DomainKnowledge"/>
    </SubClassOf>
    <SubClassOf>
        <Class IRI="#Presentation"/>
        <Class IRI="#DomainKnowledge"/>
    </SubClassOf>
    <SubClassOf>
        <Class IRI="#Rule"/>
        <Class IRI="#DomainKnowledge"/>
    </SubClassOf>
    <InverseObjectProperties>
        <ObjectProperty IRI="#influences"/>
        <ObjectProperty IRI="#requires"/>
    </InverseObjectProperties>
    <ObjectPropertyDomain>
        <ObjectProperty abbreviatedIRI="oa:hasBody"/>
        <Class abbreviatedIRI="oa:Annotation"/>
    </ObjectPropertyDomain>
    <ObjectPropertyDomain>
        <ObjectProperty abbreviatedIRI="oa:hasSelector"/>
        <Class abbreviatedIRI="oa:SpecificResource"/>
    </ObjectPropertyDomain>
    <ObjectPropertyDomain>
        <ObjectProperty abbreviatedIRI="oa:hasTarget"/>
        <Class abbreviatedIRI="oa:Annotation"/>
    </ObjectPropertyDomain>
    <ObjectPropertyDomain>
        <ObjectProperty IRI="#influences"/>
        <Class IRI="#DomainKnowledge"/>
    </ObjectPropertyDomain>
    <ObjectPropertyDomain>
        <ObjectProperty IRI="#requires"/>
        <Class IRI="#Feature"/>
    </ObjectPropertyDomain>
    <ObjectPropertyDomain>
        <ObjectProperty IRI="#within"/>
        <Class abbreviatedIRI="oa:Annotation"/>
    </ObjectPropertyDomain>
    <ObjectPropertyRange>
        <ObjectProperty abbreviatedIRI="oa:hasBody"/>
        <Class IRI="#DomainKnowledge"/>
    </ObjectPropertyRange>
    <ObjectPropertyRange>
        <ObjectProperty abbreviatedIRI="oa:hasBody"/>
        <Class IRI="#Feature"/>
    </ObjectPropertyRange>
    <ObjectPropertyRange>
        <ObjectProperty abbreviatedIRI="oa:hasSelector"/>
        <Class abbreviatedIRI="oa:TextPositionSelector"/>
    </ObjectPropertyRange>
    <ObjectPropertyRange>
        <ObjectProperty abbreviatedIRI="oa:hasTarget"/>
        <Class abbreviatedIRI="oa:SpecificResource"/>
    </ObjectPropertyRange>
    <ObjectPropertyRange>
        <ObjectProperty IRI="#influences"/>
        <Class IRI="#Feature"/>
    </ObjectPropertyRange>
    <ObjectPropertyRange>
        <ObjectProperty IRI="#requires"/>
        <Class IRI="#DomainKnowledge"/>
    </ObjectPropertyRange>
    <ObjectPropertyRange>
        <ObjectProperty IRI="#within"/>
        <Class IRI="#Area"/>
    </ObjectPropertyRange>
    <DataPropertyDomain>
        <DataProperty abbreviatedIRI="oa:end"/>
        <Class abbreviatedIRI="oa:TextPositionSelector"/>
    </DataPropertyDomain>
    <DataPropertyDomain>
        <DataProperty abbreviatedIRI="oa:hasSource"/>
        <Class abbreviatedIRI="oa:SpecificResource"/>
    </DataPropertyDomain>
    <DataPropertyDomain>
        <DataProperty abbreviatedIRI="oa:start"/>
        <Class abbreviatedIRI="oa:TextPositionSelector"/>
    </DataPropertyDomain>
    <DataPropertyDomain>
        <DataProperty IRI="#name"/>
        <Class IRI="#DomainKnowledge"/>
    </DataPropertyDomain>
    <DataPropertyDomain>
        <DataProperty IRI="#name"/>
        <Class IRI="#Feature"/>
    </DataPropertyDomain>
    <DataPropertyRange>
        <DataProperty abbreviatedIRI="oa:end"/>
        <Datatype abbreviatedIRI="xsd:integer"/>
    </DataPropertyRange>
    <DataPropertyRange>
        <DataProperty abbreviatedIRI="oa:hasSource"/>
        <Datatype abbreviatedIRI="xsd:anyURI"/>
    </DataPropertyRange>
    <DataPropertyRange>
        <DataProperty abbreviatedIRI="oa:start"/>
        <Datatype abbreviatedIRI="xsd:integer"/>
    </DataPropertyRange>
    <DataPropertyRange>
        <DataProperty IRI="#name"/>
        <Datatype abbreviatedIRI="xsd:string"/>
    </DataPropertyRange>
    <DLSafeRule>
        <Annotation>
            <AnnotationProperty abbreviatedIRI="swrla:isRuleEnabled"/>
            <Literal datatypeIRI="http://www.w3.org/2001/XMLSchema#boolean">true</Literal>
        </Annotation>
        <Annotation>
            <AnnotationProperty abbreviatedIRI="rdfs:comment"/>
            <Literal></Literal>
        </Annotation>
        <Annotation>
            <AnnotationProperty abbreviatedIRI="rdfs:label"/>
            <Literal>S5</Literal>
        </Annotation>
        <Body>
            <DataPropertyAtom>
                <DataProperty abbreviatedIRI="oa:start"/>
                <Variable IRI="#TR"/>
                <Variable IRI="#sr"/>
            </DataPropertyAtom>
            <DataPropertyAtom>
                <DataProperty abbreviatedIRI="oa:start"/>
                <Variable IRI="#TF"/>
                <Variable IRI="#sf"/>
            </DataPropertyAtom>
            <DataPropertyAtom>
                <DataProperty abbreviatedIRI="oa:hasSource"/>
                <Variable IRI="#SF"/>
                <Variable IRI="#S"/>
            </DataPropertyAtom>
            <ClassAtom>
                <Class abbreviatedIRI="oa:SpecificResource"/>
                <Variable IRI="#SR"/>
            </ClassAtom>
            <ClassAtom>
                <Class abbreviatedIRI="oa:TextPositionSelector"/>
                <Variable IRI="#TF"/>
            </ClassAtom>
            <ClassAtom>
                <Class abbreviatedIRI="oa:SpecificResource"/>
                <Variable IRI="#SF"/>
            </ClassAtom>
            <BuiltInAtom abbreviatedIRI="swrlb:greaterThanOrEqual">
                <Variable IRI="#ef"/>
                <Variable IRI="#er"/>
            </BuiltInAtom>
            <ClassAtom>
                <Class abbreviatedIRI="oa:Annotation"/>
                <Variable IRI="#AR"/>
            </ClassAtom>
            <BuiltInAtom abbreviatedIRI="swrlb:lessThan">
                <Variable IRI="#sr"/>
                <Variable IRI="#sf"/>
            </BuiltInAtom>
            <ObjectPropertyAtom>
                <ObjectProperty abbreviatedIRI="oa:hasBody"/>
                <Variable IRI="#AF"/>
                <Variable IRI="#F"/>
            </ObjectPropertyAtom>
            <ObjectPropertyAtom>
                <ObjectProperty abbreviatedIRI="oa:hasBody"/>
                <Variable IRI="#AR"/>
                <Variable IRI="#R"/>
            </ObjectPropertyAtom>
            <ClassAtom>
                <Class abbreviatedIRI="oa:TextPositionSelector"/>
                <Variable IRI="#TR"/>
            </ClassAtom>
            <ObjectPropertyAtom>
                <ObjectProperty abbreviatedIRI="oa:hasSelector"/>
                <Variable IRI="#SF"/>
                <Variable IRI="#TF"/>
            </ObjectPropertyAtom>
            <ObjectPropertyAtom>
                <ObjectProperty abbreviatedIRI="oa:hasSelector"/>
                <Variable IRI="#SR"/>
                <Variable IRI="#TR"/>
            </ObjectPropertyAtom>
            <BuiltInAtom abbreviatedIRI="swrlb:greaterThanOrEqual">
                <Variable IRI="#er"/>
                <Variable IRI="#sf"/>
            </BuiltInAtom>
            <ClassAtom>
                <Class IRI="#Feature"/>
                <Variable IRI="#F"/>
            </ClassAtom>
            <DataPropertyAtom>
                <DataProperty abbreviatedIRI="oa:end"/>
                <Variable IRI="#TR"/>
                <Variable IRI="#er"/>
            </DataPropertyAtom>
            <DataPropertyAtom>
                <DataProperty abbreviatedIRI="oa:end"/>
                <Variable IRI="#TF"/>
                <Variable IRI="#ef"/>
            </DataPropertyAtom>
            <ObjectPropertyAtom>
                <ObjectProperty abbreviatedIRI="oa:hasTarget"/>
                <Variable IRI="#AF"/>
                <Variable IRI="#SF"/>
            </ObjectPropertyAtom>
            <ObjectPropertyAtom>
                <ObjectProperty abbreviatedIRI="oa:hasTarget"/>
                <Variable IRI="#AR"/>
                <Variable IRI="#SR"/>
            </ObjectPropertyAtom>
            <DataPropertyAtom>
                <DataProperty abbreviatedIRI="oa:hasSource"/>
                <Variable IRI="#SR"/>
                <Variable IRI="#S"/>
            </DataPropertyAtom>
            <ClassAtom>
                <Class IRI="#DomainKnowledge"/>
                <Variable IRI="#R"/>
            </ClassAtom>
            <ClassAtom>
                <Class abbreviatedIRI="oa:Annotation"/>
                <Variable IRI="#AF"/>
            </ClassAtom>
        </Body>
        <Head>
            <ObjectPropertyAtom>
                <ObjectProperty IRI="#requires"/>
                <Variable IRI="#F"/>
                <Variable IRI="#R"/>
            </ObjectPropertyAtom>
            <ObjectPropertyAtom>
                <ObjectProperty IRI="#influences"/>
                <Variable IRI="#R"/>
                <Variable IRI="#F"/>
            </ObjectPropertyAtom>
        </Head>
    </DLSafeRule>
    <DLSafeRule>
        <Annotation>
            <AnnotationProperty abbreviatedIRI="swrla:isRuleEnabled"/>
            <Literal datatypeIRI="http://www.w3.org/2001/XMLSchema#boolean">true</Literal>
        </Annotation>
        <Annotation>
            <AnnotationProperty abbreviatedIRI="rdfs:comment"/>
            <Literal></Literal>
        </Annotation>
        <Annotation>
            <AnnotationProperty abbreviatedIRI="rdfs:label"/>
            <Literal>S1</Literal>
        </Annotation>
        <Body>
            <DataPropertyAtom>
                <DataProperty abbreviatedIRI="oa:start"/>
                <Variable IRI="#TR"/>
                <Variable IRI="#sr"/>
            </DataPropertyAtom>
            <DataPropertyAtom>
                <DataProperty abbreviatedIRI="oa:start"/>
                <Variable IRI="#TF"/>
                <Variable IRI="#sf"/>
            </DataPropertyAtom>
            <DataPropertyAtom>
                <DataProperty abbreviatedIRI="oa:hasSource"/>
                <Variable IRI="#SF"/>
                <Variable IRI="#S"/>
            </DataPropertyAtom>
            <ClassAtom>
                <Class abbreviatedIRI="oa:SpecificResource"/>
                <Variable IRI="#SR"/>
            </ClassAtom>
            <ClassAtom>
                <Class abbreviatedIRI="oa:TextPositionSelector"/>
                <Variable IRI="#TF"/>
            </ClassAtom>
            <ClassAtom>
                <Class abbreviatedIRI="oa:SpecificResource"/>
                <Variable IRI="#SF"/>
            </ClassAtom>
            <BuiltInAtom abbreviatedIRI="swrlb:lessThanOrEqual">
                <Variable IRI="#er"/>
                <Variable IRI="#ef"/>
            </BuiltInAtom>
            <ClassAtom>
                <Class abbreviatedIRI="oa:Annotation"/>
                <Variable IRI="#AR"/>
            </ClassAtom>
            <BuiltInAtom abbreviatedIRI="swrlb:greaterThanOrEqual">
                <Variable IRI="#sr"/>
                <Variable IRI="#sf"/>
            </BuiltInAtom>
            <ObjectPropertyAtom>
                <ObjectProperty abbreviatedIRI="oa:hasBody"/>
                <Variable IRI="#AF"/>
                <Variable IRI="#F"/>
            </ObjectPropertyAtom>
            <ObjectPropertyAtom>
                <ObjectProperty abbreviatedIRI="oa:hasBody"/>
                <Variable IRI="#AR"/>
                <Variable IRI="#R"/>
            </ObjectPropertyAtom>
            <ClassAtom>
                <Class abbreviatedIRI="oa:TextPositionSelector"/>
                <Variable IRI="#TR"/>
            </ClassAtom>
            <ObjectPropertyAtom>
                <ObjectProperty abbreviatedIRI="oa:hasSelector"/>
                <Variable IRI="#SF"/>
                <Variable IRI="#TF"/>
            </ObjectPropertyAtom>
            <ObjectPropertyAtom>
                <ObjectProperty abbreviatedIRI="oa:hasSelector"/>
                <Variable IRI="#SR"/>
                <Variable IRI="#TR"/>
            </ObjectPropertyAtom>
            <ClassAtom>
                <Class IRI="#Feature"/>
                <Variable IRI="#F"/>
            </ClassAtom>
            <DataPropertyAtom>
                <DataProperty abbreviatedIRI="oa:end"/>
                <Variable IRI="#TR"/>
                <Variable IRI="#er"/>
            </DataPropertyAtom>
            <DataPropertyAtom>
                <DataProperty abbreviatedIRI="oa:end"/>
                <Variable IRI="#TF"/>
                <Variable IRI="#ef"/>
            </DataPropertyAtom>
            <ObjectPropertyAtom>
                <ObjectProperty abbreviatedIRI="oa:hasTarget"/>
                <Variable IRI="#AF"/>
                <Variable IRI="#SF"/>
            </ObjectPropertyAtom>
            <ObjectPropertyAtom>
                <ObjectProperty abbreviatedIRI="oa:hasTarget"/>
                <Variable IRI="#AR"/>
                <Variable IRI="#SR"/>
            </ObjectPropertyAtom>
            <DataPropertyAtom>
                <DataProperty abbreviatedIRI="oa:hasSource"/>
                <Variable IRI="#SR"/>
                <Variable IRI="#S"/>
            </DataPropertyAtom>
            <ClassAtom>
                <Class IRI="#DomainKnowledge"/>
                <Variable IRI="#R"/>
            </ClassAtom>
            <ClassAtom>
                <Class abbreviatedIRI="oa:Annotation"/>
                <Variable IRI="#AF"/>
            </ClassAtom>
        </Body>
        <Head>
            <ObjectPropertyAtom>
                <ObjectProperty IRI="#requires"/>
                <Variable IRI="#F"/>
                <Variable IRI="#R"/>
            </ObjectPropertyAtom>
            <ObjectPropertyAtom>
                <ObjectProperty IRI="#influences"/>
                <Variable IRI="#R"/>
                <Variable IRI="#F"/>
            </ObjectPropertyAtom>
        </Head>
    </DLSafeRule>
    <DLSafeRule>
        <Annotation>
            <AnnotationProperty abbreviatedIRI="swrla:isRuleEnabled"/>
            <Literal datatypeIRI="http://www.w3.org/2001/XMLSchema#boolean">true</Literal>
        </Annotation>
        <Annotation>
            <AnnotationProperty abbreviatedIRI="rdfs:comment"/>
            <Literal></Literal>
        </Annotation>
        <Annotation>
            <AnnotationProperty abbreviatedIRI="rdfs:label"/>
            <Literal>S2</Literal>
        </Annotation>
        <Body>
            <DataPropertyAtom>
                <DataProperty abbreviatedIRI="oa:start"/>
                <Variable IRI="#TR"/>
                <Variable IRI="#sr"/>
            </DataPropertyAtom>
            <DataPropertyAtom>
                <DataProperty abbreviatedIRI="oa:start"/>
                <Variable IRI="#TF"/>
                <Variable IRI="#sf"/>
            </DataPropertyAtom>
            <ClassAtom>
                <Class abbreviatedIRI="oa:SpecificResource"/>
                <Variable IRI="#SR"/>
            </ClassAtom>
            <ClassAtom>
                <Class abbreviatedIRI="oa:TextPositionSelector"/>
                <Variable IRI="#TF"/>
            </ClassAtom>
            <ClassAtom>
                <Class abbreviatedIRI="oa:SpecificResource"/>
                <Variable IRI="#SF"/>
            </ClassAtom>
            <ClassAtom>
                <Class abbreviatedIRI="oa:Annotation"/>
                <Variable IRI="#AR"/>
            </ClassAtom>
            <ObjectPropertyAtom>
                <ObjectProperty abbreviatedIRI="oa:hasBody"/>
                <Variable IRI="#AF"/>
                <Variable IRI="#F"/>
            </ObjectPropertyAtom>
            <ObjectPropertyAtom>
                <ObjectProperty abbreviatedIRI="oa:hasBody"/>
                <Variable IRI="#AR"/>
                <Variable IRI="#R"/>
            </ObjectPropertyAtom>
            <ClassAtom>
                <Class abbreviatedIRI="oa:TextPositionSelector"/>
                <Variable IRI="#TR"/>
            </ClassAtom>
            <ObjectPropertyAtom>
                <ObjectProperty abbreviatedIRI="oa:hasSelector"/>
                <Variable IRI="#SF"/>
                <Variable IRI="#TF"/>
            </ObjectPropertyAtom>
            <ObjectPropertyAtom>
                <ObjectProperty abbreviatedIRI="oa:hasSelector"/>
                <Variable IRI="#SR"/>
                <Variable IRI="#TR"/>
            </ObjectPropertyAtom>
            <BuiltInAtom abbreviatedIRI="swrlb:lessThan">
                <Variable IRI="#sf"/>
                <Variable IRI="#sr"/>
            </BuiltInAtom>
            <ClassAtom>
                <Class IRI="#Feature"/>
                <Variable IRI="#F"/>
            </ClassAtom>
            <DataPropertyAtom>
                <DataProperty abbreviatedIRI="oa:end"/>
                <Variable IRI="#TR"/>
                <Variable IRI="#er"/>
            </DataPropertyAtom>
            <DataPropertyAtom>
                <DataProperty abbreviatedIRI="oa:end"/>
                <Variable IRI="#TF"/>
                <Variable IRI="#ef"/>
            </DataPropertyAtom>
            <ObjectPropertyAtom>
                <ObjectProperty abbreviatedIRI="oa:hasTarget"/>
                <Variable IRI="#AF"/>
                <Variable IRI="#SF"/>
            </ObjectPropertyAtom>
            <ObjectPropertyAtom>
                <ObjectProperty abbreviatedIRI="oa:hasTarget"/>
                <Variable IRI="#AR"/>
                <Variable IRI="#SR"/>
            </ObjectPropertyAtom>
            <BuiltInAtom abbreviatedIRI="swrlb:greaterThanOrEqual">
                <Variable IRI="#ef"/>
                <Variable IRI="#sr"/>
            </BuiltInAtom>
            <BuiltInAtom abbreviatedIRI="swrlb:greaterThan">
                <Variable IRI="#er"/>
                <Variable IRI="#ef"/>
            </BuiltInAtom>
            <ClassAtom>
                <Class IRI="#DomainKnowledge"/>
                <Variable IRI="#R"/>
            </ClassAtom>
            <ClassAtom>
                <Class abbreviatedIRI="oa:Annotation"/>
                <Variable IRI="#AF"/>
            </ClassAtom>
        </Body>
        <Head>
            <ObjectPropertyAtom>
                <ObjectProperty IRI="#requires"/>
                <Variable IRI="#F"/>
                <Variable IRI="#R"/>
            </ObjectPropertyAtom>
            <ObjectPropertyAtom>
                <ObjectProperty IRI="#influences"/>
                <Variable IRI="#R"/>
                <Variable IRI="#F"/>
            </ObjectPropertyAtom>
        </Head>
    </DLSafeRule>
    <DLSafeRule>
        <Annotation>
            <AnnotationProperty abbreviatedIRI="swrla:isRuleEnabled"/>
            <Literal datatypeIRI="http://www.w3.org/2001/XMLSchema#boolean">true</Literal>
        </Annotation>
        <Annotation>
            <AnnotationProperty abbreviatedIRI="rdfs:comment"/>
            <Literal></Literal>
        </Annotation>
        <Annotation>
            <AnnotationProperty abbreviatedIRI="rdfs:label"/>
            <Literal>S3</Literal>
        </Annotation>
        <Body>
            <DataPropertyAtom>
                <DataProperty abbreviatedIRI="oa:start"/>
                <Variable IRI="#TR"/>
                <Variable IRI="#sr"/>
            </DataPropertyAtom>
            <DataPropertyAtom>
                <DataProperty abbreviatedIRI="oa:start"/>
                <Variable IRI="#TF"/>
                <Variable IRI="#sf"/>
            </DataPropertyAtom>
            <ClassAtom>
                <Class abbreviatedIRI="oa:SpecificResource"/>
                <Variable IRI="#SR"/>
            </ClassAtom>
            <ClassAtom>
                <Class abbreviatedIRI="oa:TextPositionSelector"/>
                <Variable IRI="#TF"/>
            </ClassAtom>
            <ClassAtom>
                <Class abbreviatedIRI="oa:SpecificResource"/>
                <Variable IRI="#SF"/>
            </ClassAtom>
            <BuiltInAtom abbreviatedIRI="swrlb:greaterThanOrEqual">
                <Variable IRI="#ef"/>
                <Variable IRI="#er"/>
            </BuiltInAtom>
            <ClassAtom>
                <Class abbreviatedIRI="oa:Annotation"/>
                <Variable IRI="#AR"/>
            </ClassAtom>
            <ObjectPropertyAtom>
                <ObjectProperty abbreviatedIRI="oa:hasBody"/>
                <Variable IRI="#AF"/>
                <Variable IRI="#F"/>
            </ObjectPropertyAtom>
            <ObjectPropertyAtom>
                <ObjectProperty abbreviatedIRI="oa:hasBody"/>
                <Variable IRI="#AR"/>
                <Variable IRI="#R"/>
            </ObjectPropertyAtom>
            <ClassAtom>
                <Class abbreviatedIRI="oa:TextPositionSelector"/>
                <Variable IRI="#TR"/>
            </ClassAtom>
            <ObjectPropertyAtom>
                <ObjectProperty abbreviatedIRI="oa:hasSelector"/>
                <Variable IRI="#SF"/>
                <Variable IRI="#TF"/>
            </ObjectPropertyAtom>
            <ObjectPropertyAtom>
                <ObjectProperty abbreviatedIRI="oa:hasSelector"/>
                <Variable IRI="#SR"/>
                <Variable IRI="#TR"/>
            </ObjectPropertyAtom>
            <ClassAtom>
                <Class IRI="#Feature"/>
                <Variable IRI="#F"/>
            </ClassAtom>
            <DataPropertyAtom>
                <DataProperty abbreviatedIRI="oa:end"/>
                <Variable IRI="#TR"/>
                <Variable IRI="#er"/>
            </DataPropertyAtom>
            <DataPropertyAtom>
                <DataProperty abbreviatedIRI="oa:end"/>
                <Variable IRI="#TF"/>
                <Variable IRI="#ef"/>
            </DataPropertyAtom>
            <ObjectPropertyAtom>
                <ObjectProperty abbreviatedIRI="oa:hasTarget"/>
                <Variable IRI="#AF"/>
                <Variable IRI="#SF"/>
            </ObjectPropertyAtom>
            <ObjectPropertyAtom>
                <ObjectProperty abbreviatedIRI="oa:hasTarget"/>
                <Variable IRI="#AR"/>
                <Variable IRI="#SR"/>
            </ObjectPropertyAtom>
            <BuiltInAtom abbreviatedIRI="swrlb:lessThanOrEqual">
                <Variable IRI="#sf"/>
                <Variable IRI="#sr"/>
            </BuiltInAtom>
            <ClassAtom>
                <Class IRI="#DomainKnowledge"/>
                <Variable IRI="#R"/>
            </ClassAtom>
            <ClassAtom>
                <Class abbreviatedIRI="oa:Annotation"/>
                <Variable IRI="#AF"/>
            </ClassAtom>
        </Body>
        <Head>
            <ObjectPropertyAtom>
                <ObjectProperty IRI="#requires"/>
                <Variable IRI="#F"/>
                <Variable IRI="#R"/>
            </ObjectPropertyAtom>
            <ObjectPropertyAtom>
                <ObjectProperty IRI="#influences"/>
                <Variable IRI="#R"/>
                <Variable IRI="#F"/>
            </ObjectPropertyAtom>
        </Head>
    </DLSafeRule>
    <DLSafeRule>
        <Annotation>
            <AnnotationProperty abbreviatedIRI="swrla:isRuleEnabled"/>
            <Literal datatypeIRI="http://www.w3.org/2001/XMLSchema#boolean">true</Literal>
        </Annotation>
        <Annotation>
            <AnnotationProperty abbreviatedIRI="rdfs:comment"/>
            <Literal></Literal>
        </Annotation>
        <Annotation>
            <AnnotationProperty abbreviatedIRI="rdfs:label"/>
            <Literal>S4</Literal>
        </Annotation>
        <Body>
            <DataPropertyAtom>
                <DataProperty abbreviatedIRI="oa:start"/>
                <Variable IRI="#TR"/>
                <Variable IRI="#sr"/>
            </DataPropertyAtom>
            <DataPropertyAtom>
                <DataProperty abbreviatedIRI="oa:start"/>
                <Variable IRI="#TF"/>
                <Variable IRI="#sf"/>
            </DataPropertyAtom>
            <BuiltInAtom abbreviatedIRI="swrlb:greaterThanOrEqual">
                <Variable IRI="#er"/>
                <Variable IRI="#ef"/>
            </BuiltInAtom>
            <ClassAtom>
                <Class abbreviatedIRI="oa:SpecificResource"/>
                <Variable IRI="#SR"/>
            </ClassAtom>
            <ClassAtom>
                <Class abbreviatedIRI="oa:TextPositionSelector"/>
                <Variable IRI="#TF"/>
            </ClassAtom>
            <ClassAtom>
                <Class abbreviatedIRI="oa:SpecificResource"/>
                <Variable IRI="#SF"/>
            </ClassAtom>
            <ClassAtom>
                <Class abbreviatedIRI="oa:Annotation"/>
                <Variable IRI="#AR"/>
            </ClassAtom>
            <ObjectPropertyAtom>
                <ObjectProperty abbreviatedIRI="oa:hasBody"/>
                <Variable IRI="#AF"/>
                <Variable IRI="#F"/>
            </ObjectPropertyAtom>
            <ObjectPropertyAtom>
                <ObjectProperty abbreviatedIRI="oa:hasBody"/>
                <Variable IRI="#AR"/>
                <Variable IRI="#R"/>
            </ObjectPropertyAtom>
            <ClassAtom>
                <Class abbreviatedIRI="oa:TextPositionSelector"/>
                <Variable IRI="#TR"/>
            </ClassAtom>
            <ObjectPropertyAtom>
                <ObjectProperty abbreviatedIRI="oa:hasSelector"/>
                <Variable IRI="#SF"/>
                <Variable IRI="#TF"/>
            </ObjectPropertyAtom>
            <ObjectPropertyAtom>
                <ObjectProperty abbreviatedIRI="oa:hasSelector"/>
                <Variable IRI="#SR"/>
                <Variable IRI="#TR"/>
            </ObjectPropertyAtom>
            <BuiltInAtom abbreviatedIRI="swrlb:lessThanOrEqual">
                <Variable IRI="#sr"/>
                <Variable IRI="#sf"/>
            </BuiltInAtom>
            <ClassAtom>
                <Class IRI="#Feature"/>
                <Variable IRI="#F"/>
            </ClassAtom>
            <DataPropertyAtom>
                <DataProperty abbreviatedIRI="oa:end"/>
                <Variable IRI="#TR"/>
                <Variable IRI="#er"/>
            </DataPropertyAtom>
            <DataPropertyAtom>
                <DataProperty abbreviatedIRI="oa:end"/>
                <Variable IRI="#TF"/>
                <Variable IRI="#ef"/>
            </DataPropertyAtom>
            <ObjectPropertyAtom>
                <ObjectProperty abbreviatedIRI="oa:hasTarget"/>
                <Variable IRI="#AF"/>
                <Variable IRI="#SF"/>
            </ObjectPropertyAtom>
            <ObjectPropertyAtom>
                <ObjectProperty abbreviatedIRI="oa:hasTarget"/>
                <Variable IRI="#AR"/>
                <Variable IRI="#SR"/>
            </ObjectPropertyAtom>
            <ClassAtom>
                <Class IRI="#DomainKnowledge"/>
                <Variable IRI="#R"/>
            </ClassAtom>
            <ClassAtom>
                <Class abbreviatedIRI="oa:Annotation"/>
                <Variable IRI="#AF"/>
            </ClassAtom>
        </Body>
        <Head>
            <ObjectPropertyAtom>
                <ObjectProperty IRI="#requires"/>
                <Variable IRI="#F"/>
                <Variable IRI="#R"/>
            </ObjectPropertyAtom>
            <ObjectPropertyAtom>
                <ObjectProperty IRI="#influences"/>
                <Variable IRI="#R"/>
                <Variable IRI="#F"/>
            </ObjectPropertyAtom>
        </Head>
    </DLSafeRule>
    <DLSafeRule>
        <Annotation>
            <AnnotationProperty abbreviatedIRI="swrla:isRuleEnabled"/>
            <Literal datatypeIRI="http://www.w3.org/2001/XMLSchema#boolean">true</Literal>
        </Annotation>
        <Annotation>
            <AnnotationProperty abbreviatedIRI="rdfs:comment"/>
            <Literal></Literal>
        </Annotation>
        <Annotation>
            <AnnotationProperty abbreviatedIRI="rdfs:label"/>
            <Literal>AnnotationWithinArea</Literal>
        </Annotation>
        <Body>
            <ClassAtom>
                <Class abbreviatedIRI="oa:Annotation"/>
                <Variable IRI="#AN"/>
            </ClassAtom>
            <ClassAtom>
                <Class IRI="#Area"/>
                <Variable IRI="#AREA"/>
            </ClassAtom>
            <ObjectPropertyAtom>
                <ObjectProperty abbreviatedIRI="oa:hasTarget"/>
                <Variable IRI="#AN"/>
                <Variable IRI="#SR"/>
            </ObjectPropertyAtom>
            <ClassAtom>
                <Class abbreviatedIRI="oa:SpecificResource"/>
                <Variable IRI="#SR"/>
            </ClassAtom>
            <DataPropertyAtom>
                <DataProperty abbreviatedIRI="oa:hasSource"/>
                <Variable IRI="#SR"/>
                <Variable IRI="#SOURCE"/>
            </DataPropertyAtom>
            <DataPropertyAtom>
                <DataProperty abbreviatedIRI="oa:hasSource"/>
                <Variable IRI="#AREA"/>
                <Variable IRI="#SOURCE"/>
            </DataPropertyAtom>
            <ClassAtom>
                <Class abbreviatedIRI="oa:TextPositionSelector"/>
                <Variable IRI="#TAN"/>
            </ClassAtom>
            <ClassAtom>
                <Class abbreviatedIRI="oa:TextPositionSelector"/>
                <Variable IRI="#TAR"/>
            </ClassAtom>
            <DataPropertyAtom>
                <DataProperty abbreviatedIRI="oa:start"/>
                <Variable IRI="#TAN"/>
                <Variable IRI="#san"/>
            </DataPropertyAtom>
            <DataPropertyAtom>
                <DataProperty abbreviatedIRI="oa:start"/>
                <Variable IRI="#TAR"/>
                <Variable IRI="#sar"/>
            </DataPropertyAtom>
            <DataPropertyAtom>
                <DataProperty abbreviatedIRI="oa:end"/>
                <Variable IRI="#TAN"/>
                <Variable IRI="#ean"/>
            </DataPropertyAtom>
            <DataPropertyAtom>
                <DataProperty abbreviatedIRI="oa:end"/>
                <Variable IRI="#TAR"/>
                <Variable IRI="#ear"/>
            </DataPropertyAtom>
            <BuiltInAtom abbreviatedIRI="swrlb:lessThanOrEqual">
                <Variable IRI="#sar"/>
                <Variable IRI="#san"/>
            </BuiltInAtom>
            <BuiltInAtom abbreviatedIRI="swrlb:greaterThanOrEqual">
                <Variable IRI="#ear"/>
                <Variable IRI="#ean"/>
            </BuiltInAtom>
        </Body>
        <Head>
            <ObjectPropertyAtom>
                <ObjectProperty IRI="#within"/>
                <Variable IRI="#AN"/>
                <Variable IRI="#AREA"/>
            </ObjectPropertyAtom>
        </Head>
    </DLSafeRule>
    <AnnotationAssertion>
        <AnnotationProperty abbreviatedIRI="rdfs:seeAlso"/>
        <AbbreviatedIRI>oa:Annotation</AbbreviatedIRI>
        <IRI>kdm:Annotation</IRI>
    </AnnotationAssertion>
    <AnnotationAssertion>
        <AnnotationProperty abbreviatedIRI="rdfs:seeAlso"/>
        <AbbreviatedIRI>oa:SpecificResource</AbbreviatedIRI>
        <IRI>kdm:SourceFile</IRI>
    </AnnotationAssertion>
    <AnnotationAssertion>
        <AnnotationProperty abbreviatedIRI="rdfs:seeAlso"/>
        <AbbreviatedIRI>oa:SpecificResource</AbbreviatedIRI>
        <IRI>kdm:SourceRef</IRI>
    </AnnotationAssertion>
    <AnnotationAssertion>
        <AnnotationProperty abbreviatedIRI="rdfs:seeAlso"/>
        <AbbreviatedIRI>oa:TextPositionSelector</AbbreviatedIRI>
        <IRI>kdm:SourceRegion</IRI>
    </AnnotationAssertion>
    <AnnotationAssertion>
        <AnnotationProperty abbreviatedIRI="rdfs:seeAlso"/>
        <AbbreviatedIRI>oa:hasSelector</AbbreviatedIRI>
        <IRI>kdm:SourceRef</IRI>
    </AnnotationAssertion>
    <AnnotationAssertion>
        <AnnotationProperty abbreviatedIRI="rdfs:seeAlso"/>
        <AbbreviatedIRI>oa:hasTarget</AbbreviatedIRI>
        <IRI>kdm:SourceFile</IRI>
    </AnnotationAssertion>
    <AnnotationAssertion>
        <AnnotationProperty abbreviatedIRI="rdfs:seeAlso"/>
        <IRI>#Algorithm</IRI>
        <IRI>kdm:BehaviorUnit</IRI>
    </AnnotationAssertion>
    <AnnotationAssertion>
        <AnnotationProperty abbreviatedIRI="rdfs:seeAlso"/>
        <IRI>#BusinessProccess</IRI>
        <IRI>kdm:ConceptualFlow</IRI>
    </AnnotationAssertion>
    <AnnotationAssertion>
        <AnnotationProperty abbreviatedIRI="rdfs:seeAlso"/>
        <IRI>#Configuration</IRI>
        <IRI>kdm:ConfigFile</IRI>
    </AnnotationAssertion>
    <AnnotationAssertion>
        <AnnotationProperty abbreviatedIRI="rdfs:seeAlso"/>
        <IRI>#Explanatory</IRI>
        <IRI>kdm:CommentUnit</IRI>
    </AnnotationAssertion>
    <AnnotationAssertion>
        <AnnotationProperty abbreviatedIRI="rdfs:seeAlso"/>
        <IRI>#Rule</IRI>
        <IRI>kdm:RuleUnit</IRI>
    </AnnotationAssertion>
</Ontology>



<!-- Generated by the OWL API (version 4.5.7.2018-12-02T02:23:35Z) https://github.com/owlcs/owlapi -->

